fastpdf/__init__.py
fastpdf/api.py
fastpdf/exceptions.py
fastpdf/models.py
fastpdf-1.0.4.dist-info/METADATA
fastpdf-1.0.4.dist-info/WHEEL
fastpdf-1.0.4.dist-info/top_level.txt
fastpdf-1.0.4.dist-info/RECORD
