Metadata-Version: 2.1
Name: fastpdf
Version: 1.0.4
Summary: SDK for PDF rendering, generation & transformation via Fast PDF Service.
Home-page: https://github.com/fastpdfservices/fastpdf-python
Author: Korian
Author-email: korian@fastpdfservice.com
License: MIT
Platform: UNKNOWN
Classifier: License :: OSI Approved :: MIT License
Classifier: Programming Language :: Python :: 3.6
Classifier: Programming Language :: Python :: 3.7
Classifier: Programming Language :: Python :: 3.8
Classifier: Programming Language :: Python :: 3.9
Classifier: Programming Language :: Python :: 3.10
Classifier: Programming Language :: Python :: 3.11
Classifier: Programming Language :: Python :: 3.12
Requires-Dist: python-magic
Requires-Dist: requests
